jaalvarez2818_airport_docs/__init__.py
jaalvarez2818_airport_docs/api.py
jaalvarez2818_airport_docs/normalize.py
jaalvarez2818_airport_docs/pnl.py
jaalvarez2818_airport_docs/entities/__init__.py
jaalvarez2818_airport_docs/entities/contact_info.py
jaalvarez2818_airport_docs/entities/flight.py
jaalvarez2818_airport_docs/entities/pax.py
jaalvarez2818_airport_docs-0.8.5.dist-info/METADATA
jaalvarez2818_airport_docs-0.8.5.dist-info/WHEEL
jaalvarez2818_airport_docs-0.8.5.dist-info/top_level.txt
jaalvarez2818_airport_docs-0.8.5.dist-info/RECORD
